docx2markdown/__init__.py
docx2markdown/_docx_to_markdown.py
docx2markdown/_markdown_to_docx.py
docx2markdown/_terminal.py
docx2markdown-0.1.1.dist-info/LICENSE
docx2markdown-0.1.1.dist-info/METADATA
docx2markdown-0.1.1.dist-info/WHEEL
docx2markdown-0.1.1.dist-info/entry_points.txt
docx2markdown-0.1.1.dist-info/top_level.txt
docx2markdown-0.1.1.dist-info/RECORD
