Metadata-Version: 2.1
Name: docx2markdown
Version: 0.1.1
Summary: Convert simple .docx files to markdown
Home-page: https://github.com/haesleinhuepf/docx2markdown
Author: Robert Haase
Author-email: robert.haase@uni-leipzig.de
License: BSD-3-Clause
Project-URL: Bug Tracker, https://github.com/haesleinhuepf/docx2markdown/issues
Project-URL: Documentation, https://github.com/haesleinhuepf/docx2markdown#README.md
Project-URL: Source Code, https://github.com/haesleinhuepf/docx2markdown
Project-URL: User Support, https://github.com/haesleinhuepf/docx2markdown/issues
Classifier: Development Status :: 2 - Pre-Alpha
Classifier: Intended Audience :: Developers
Classifier: License :: OSI Approved :: BSD License
Classifier: Operating System :: OS Independent
Classifier: Programming Language :: Python
Classifier: Programming Language :: Python :: 3
Classifier: Programming Language :: Python :: 3.9
Classifier: Programming Language :: Python :: 3.10
Classifier: Programming Language :: Python :: 3.11
Requires-Python: >=3.9
License-File: LICENSE
Requires-Dist: python-docx
Requires-Dist: lxml
Provides-Extra: testing
Requires-Dist: tox; extra == "testing"
Requires-Dist: pytest; extra == "testing"
Requires-Dist: pytest-cov; extra == "testing"
